pyrend/__init__.py
pyrend/files.py
pyrend/input.py
pyrend/overlay.py
pyrend/sound.py
pyrend/__pycache__/__init__.cpython-313.pyc
pyrend/__pycache__/files.cpython-313.pyc
pyrend/__pycache__/input.cpython-313.pyc
pyrend/__pycache__/overlay.cpython-313.pyc
pyrend/__pycache__/sound.cpython-313.pyc
pyrend-0.1.50.dist-info/licenses/LICENSE
pyrend-0.1.50.dist-info/METADATA
pyrend-0.1.50.dist-info/WHEEL
pyrend-0.1.50.dist-info/top_level.txt
pyrend-0.1.50.dist-info/RECORD
