Metadata-Version: 2.4
Name: pyrend
Version: 0.1.50
Summary: Audio/video overlay, recording, input automation and window/file management utilities
Author-email: Caleb Keenan <caleb.keenan145@gmail.com>
License: MIT License
Classifier: Development Status :: 4 - Beta
Classifier: Intended Audience :: Developers
Classifier: License :: OSI Approved :: MIT License
Classifier: Programming Language :: Python :: 3
Classifier: Programming Language :: Python :: 3.8
Classifier: Topic :: Multimedia :: Sound/Audio
Classifier: Topic :: Software Development :: Libraries
Classifier: Topic :: Utilities
Requires-Python: >=3.8
License-File: LICENSE
Requires-Dist: PyQt5>=5.15
Requires-Dist: opencv-python>=4.5
Requires-Dist: sounddevice>=0.4.7
Requires-Dist: numpy>=1.24
Requires-Dist: soundfile>=0.11
Requires-Dist: librosa>=0.10
Requires-Dist: moviepy>=2.0
Requires-Dist: pygetwindow>=0.0.9
Requires-Dist: requests>=2.28
Requires-Dist: Pillow>=9.0
Requires-Dist: mss>=7.0
Requires-Dist: pywin32>=311
Provides-Extra: dev
Requires-Dist: pytest>=7.0; extra == "dev"
Requires-Dist: flake8>=5.0; extra == "dev"
Requires-Dist: build; extra == "dev"
Requires-Dist: twine; extra == "dev"
Dynamic: license-file
